trytond/modules/health_qrcodes/COPYING
trytond/modules/health_qrcodes/README.rst
trytond/modules/health_qrcodes/__init__.py
trytond/modules/health_qrcodes/health_qrcodes.py
trytond/modules/health_qrcodes/health_qrcodes_report.xml
trytond/modules/health_qrcodes/health_qrcodes_view.xml
trytond/modules/health_qrcodes/locale/ar.po
trytond/modules/health_qrcodes/locale/de.po
trytond/modules/health_qrcodes/locale/el.po
trytond/modules/health_qrcodes/locale/eo.po
trytond/modules/health_qrcodes/locale/es.po
trytond/modules/health_qrcodes/locale/fr.po
trytond/modules/health_qrcodes/locale/health_qrcodes.pot
trytond/modules/health_qrcodes/locale/it_IT.po
trytond/modules/health_qrcodes/locale/ja_JP.po
trytond/modules/health_qrcodes/locale/ka.po
trytond/modules/health_qrcodes/locale/lo.po
trytond/modules/health_qrcodes/locale/pt_BR.po
trytond/modules/health_qrcodes/locale/sv.po
trytond/modules/health_qrcodes/locale/tr.po
trytond/modules/health_qrcodes/locale/uk.po
trytond/modules/health_qrcodes/locale/zh_CN.po
trytond/modules/health_qrcodes/pyproject.toml
trytond/modules/health_qrcodes/report/appointment_qrcode.fodt
trytond/modules/health_qrcodes/report/barcode39.fodt
trytond/modules/health_qrcodes/report/labtest_qrcode.fodt
trytond/modules/health_qrcodes/report/newborn_card.fodt
trytond/modules/health_qrcodes/report/party_wristband.fodt
trytond/modules/health_qrcodes/report/patient_card.fodt
trytond/modules/health_qrcodes/report/patient_wristband.fodt
trytond/modules/health_qrcodes/tests/__init__.py
trytond/modules/health_qrcodes/tests/test_health_qrcodes.py
trytond/modules/health_qrcodes/tryton.cfg
trytond/modules/health_qrcodes/view/gnuhealth_appointment.xml
trytond/modules/health_qrcodes/view/gnuhealth_party_form.xml
trytond/modules/health_qrcodes/view/gnuhealth_patient_form.xml
trytond/modules/health_qrcodes/view/lab_form.xml
trytond/modules/health_qrcodes/view/newborn_form.xml
gnuhealth_qrcodes-5.0.2.dist-info/METADATA
gnuhealth_qrcodes-5.0.2.dist-info/WHEEL
gnuhealth_qrcodes-5.0.2.dist-info/licenses/COPYING
gnuhealth_qrcodes-5.0.2.dist-info/RECORD
